math_trainer/main.py
math_trainer/ui.ui
math_trainer/locales/ui_de.qm
math_trainer/locales/ui_fr.qm
math_trainer/locales/ui_ru.qm
math_trainer/locales/ui_uk.qm
math_trainer/sounds/bell.wav
math_trainer/sounds/losetrumpet.wav
math_trainer-1.2.0.dist-info/LICENSE
math_trainer-1.2.0.dist-info/METADATA
math_trainer-1.2.0.dist-info/WHEEL
math_trainer-1.2.0.dist-info/entry_points.txt
math_trainer-1.2.0.dist-info/top_level.txt
math_trainer-1.2.0.dist-info/RECORD
