Metadata-Version: 2.1
Name: math-trainer
Version: 1.2.0
Summary: A math trainer for kids written in Python and PyQt 6.
Author-email: limafresh <limafresh@proton.me>
License: GNU GENERAL PUBLIC LICENSE
Project-URL: Repository, https://github.com/limafresh/MathTrainer
Project-URL: Issues, https://github.com/limafresh/MathTrainer/issues
Keywords: math-trainer,project,pyqt,pyqt6,educational,pip,gui-project
Classifier: Development Status :: 5 - Production/Stable
Classifier: License :: OSI Approved :: GNU General Public License v3 (GPLv3)
Classifier: Programming Language :: Python :: 3
Classifier: Operating System :: OS Independent
Classifier: Intended Audience :: End Users/Desktop
Classifier: Environment :: X11 Applications :: Qt
Classifier: Topic :: Education
Classifier: Topic :: Scientific/Engineering :: Mathematics
Classifier: Natural Language :: Ukrainian
Classifier: Natural Language :: Russian
Classifier: Natural Language :: English
Requires-Python: >=3.8
License-File: LICENSE
Requires-Dist: PyQt6>=6.4.2
